datakart/__init__.py
datakart/core/datagokr.py
datakart/core/ecos.py
datakart/core/fss.py
datakart/core/jusogokr.py
datakart/core/kakao.py
datakart/core/kis.py
datakart/core/naver.py
datakart/core/naver_ad.py
datakart/core/sgis.py
datakart/core/assets/_converter.py
datakart/core/assets/adm_codes.md
datakart/core/assets/adm_codes_2306.json
datakart/core/assets/commands.md
datakart/core/assets/naver_ad_biztp.json
datakart/core/assets/naver_ad_event.json
datakart-1.23.dist-info/METADATA
datakart-1.23.dist-info/WHEEL
datakart-1.23.dist-info/licenses/LICENSE
datakart-1.23.dist-info/RECORD
