Metadata-Version: 2.4
Name: datakart
Version: 1.23
Summary: datakart package for fetching data
Project-URL: Homepage, https://github.com/himoon/datakart
Project-URL: Issues, https://github.com/himoon/datakart/issues
Author-email: HYUNIL MOON <hyunil.moon@gmail.com>
License:                                  Apache License
License-File: LICENSE
Keywords: ECOS,FSS,K-data,Kakao,NAVER,SGIS,data,data.go.kr,datakart,ecos.bok.or.kr,fss.or.kr,juso.go.kr,kart,kostat.go.kr
Classifier: License :: OSI Approved :: Apache Software License
Classifier: Operating System :: OS Independent
Classifier: Programming Language :: Python :: 3
Requires-Python: >=3.7
Requires-Dist: python-dateutil
Requires-Dist: ratelimit
Requires-Dist: requests<3,>=2
Requires-Dist: xmltodict
